odoo/addons/purchase_return/README.rst
odoo/addons/purchase_return/__init__.py
odoo/addons/purchase_return/__manifest__.py
odoo/addons/purchase_return/data/mail_template_data.xml
odoo/addons/purchase_return/data/purchase_data.xml
odoo/addons/purchase_return/i18n/it.po
odoo/addons/purchase_return/i18n/purchase_return.pot
odoo/addons/purchase_return/migrations/16.0.1.0.2/post-migration.py
odoo/addons/purchase_return/models/__init__.py
odoo/addons/purchase_return/models/account_move.py
odoo/addons/purchase_return/models/account_move_line.py
odoo/addons/purchase_return/models/product_category.py
odoo/addons/purchase_return/models/product_template.py
odoo/addons/purchase_return/models/purchase_return_order.py
odoo/addons/purchase_return/models/purchase_return_order_line.py
odoo/addons/purchase_return/readme/CONTRIBUTORS.rst
odoo/addons/purchase_return/readme/DESCRIPTION.rst
odoo/addons/purchase_return/readme/USAGE.rst
odoo/addons/purchase_return/report/purchase_reports.xml
odoo/addons/purchase_return/report/purchase_return_order_templates.xml
odoo/addons/purchase_return/security/ir.model.access.csv
odoo/addons/purchase_return/security/purchase_security.xml
odoo/addons/purchase_return/static/description/icon.png
odoo/addons/purchase_return/static/description/index.html
odoo/addons/purchase_return/tests/__init__.py
odoo/addons/purchase_return/tests/test_purchase_return_order.py
odoo/addons/purchase_return/tests/test_purchase_return_order_line.py
odoo/addons/purchase_return/views/account_move_views.xml
odoo/addons/purchase_return/views/product_category_views.xml
odoo/addons/purchase_return/views/product_template_views.xml
odoo/addons/purchase_return/views/purchase_return_template.xml
odoo/addons/purchase_return/views/purchase_views.xml
odoo_addon_purchase_return-16.0.1.0.3.1.dist-info/METADATA
odoo_addon_purchase_return-16.0.1.0.3.1.dist-info/WHEEL
odoo_addon_purchase_return-16.0.1.0.3.1.dist-info/top_level.txt
odoo_addon_purchase_return-16.0.1.0.3.1.dist-info/RECORD
